django_inbound_email-0.12.dist-info/METADATA
django_inbound_email-0.12.dist-info/RECORD
django_inbound_email-0.12.dist-info/WHEEL
django_inbound_email-0.12.dist-info/top_level.txt
inbound_email/__init__.py
inbound_email/apps.py
inbound_email/compat.py
inbound_email/errors.py
inbound_email/models.py
inbound_email/signals.py
inbound_email/urls.py
inbound_email/views.py
inbound_email/backends/__init__.py
inbound_email/backends/mailgun.py
inbound_email/backends/mandrill.py
inbound_email/backends/sendgrid.py
inbound_email/tests/__init__.py
inbound_email/tests/test_mailgun.py
inbound_email/tests/test_mandrill.py
inbound_email/tests/test_sendgrid.py
inbound_email/tests/test_views.py
inbound_email/tests/test_files/__init__.py
inbound_email/tests/test_files/mailgun_post.py
inbound_email/tests/test_files/mandrill_post.py
inbound_email/tests/test_files/sendgrid_post.py
inbound_email/tests/test_files/sendgrid_post_windows_1252.py
