Metadata-Version: 2.1
Name: django-inbound-email
Version: 0.12
Summary: A Django app for receiving inbound emails.
Home-page: https://github.com/yunojuno/django-inbound-email
Author: YunoJuno
Author-email: code@yunojuno.com
License: MIT
Platform: UNKNOWN
Classifier: Environment :: Web Environment
Classifier: Framework :: Django
Classifier: Framework :: Django :: 1.11
Classifier: Framework :: Django :: 2.0
Classifier: Intended Audience :: Developers
Classifier: License :: OSI Approved :: MIT License
Classifier: Operating System :: OS Independent
Classifier: Programming Language :: Python
Classifier: Programming Language :: Python :: 3.6
Classifier: Topic :: Internet :: WWW/HTTP
Classifier: Topic :: Internet :: WWW/HTTP :: Dynamic Content
Requires-Dist: Django (>=1.11)
